eaiesbintern1/__init__.py
eaiesbintern1-0.2.dist-info/LICENCE.txt
eaiesbintern1-0.2.dist-info/METADATA
eaiesbintern1-0.2.dist-info/WHEEL
eaiesbintern1-0.2.dist-info/top_level.txt
eaiesbintern1-0.2.dist-info/RECORD
