Metadata-Version: 2.1
Name: eaiesbintern1
Version: 0.2
Summary: calculator
Home-page: UNKNOWN
Author: Ishaan
Author-email: ishaanpandey31@gmail.com
License: UNKNOWN
Platform: UNKNOWN
Classifier: Programming Language :: Python :: 3
Classifier: License :: OSI Approved :: MIT License
Classifier: Operating System :: OS Independent
License-File: LICENCE.txt
